[
  {
   "id":"style_gigant",
   "type": "martial_art",
   "name": "Gigant Arts",
   "description": "For too long, the art of the Gigant remained beyond the realm of perception. Now, you practice as one of them.",
   "initiate": [ "It begins.", "%s gets into position."],
   "learn_difficulty": 1,
   "arm_block": 1,
   "leg_block": 1,
   "static_buffs": [
     {
       "id": "gigant_static_1",
       "name": "Stance Gigantus",
       "description": "The world approaches, you stand ready to intercept.",
       "unarmed_allowed": true,
       "melee_allowed": true,
       "bonus_blocks": 2
     },
     {
       "id": "gigant_static_2",
       "name": "Kaes",
       "description": "You make yourself scarce as enemies approach, their attacks whiffing wind",
       "skill_requirements": [
         {"name": "unarmed", "level": 5 },
         {"name": "melee", "level": 1 },
         {"name": "dodge", "level": 2 }
       ],
       "bonus_dodges": 1
     }
   ],
   "onmove_buffs": [
     {
      "id":"gigant_action_flow",
      "name": "Gigant Flow",
      "description": "Reality weaves around you, attempting to nest you in its grand scheme. You refuse.",
      "skill_requirements": [
        {"name": "dodge", "level": 3 }
      ],
      "buff_duration": 2,
      "max_stacks": 1,
      "bonus_dodges": 1,
      "flat_bonuses": [
        [ "armor", "electric", 1.0 ]
      ]
    }
   ],
   "techniques": [ "tec_gigant_push", "tec_gigant_trip", "tec_gigant_redirect", "tec_gigant_brutal", "tec_gigant_counter", "tec_gigant_dodge", "tec_gigant_direct", "tec_gigant_eviscerate", "tec_gigant_flurry", "tec_gigant_warp" ],
   "weapons":[
     "avm_sword",
     "avm_blade",
     "avm_greatsword",
     "avm_spear",
     "avm_staff",
     "avm_hammer",
     "avm_baton",
     "avm_mace",
     "sword_wood",
     "sword_nail",
     "sword_crude",
     "firekatana_off",
     "firekatana_on",
     "katana",
     "bokken",
     "cudgel",
     "q_staff",
     "i_staff",
     "lajatang",
     "wakizashi",
     "broadfire_off",
     "broadfire_on",
     "broadsword",
     "cutlass",
     "kris",
     "knife_combat",
     "knife_rambo",
     "knife_rm42",
     "knife_trench",
     "kukri",
     "tanto",
     "punch_dagger",
     "bagh_nakha",
     "cestus",
     "knuckle_brass",
     "knuckle_steel",
     "combatsaw_off",
     "combatsaw_on",
     "cs_lajatang_off",
     "cs_lajatang_on",
     "scythe",
     "scythe_war",
     "tonfa",
     "tonfa_wood",
     "survivor_machete",
     "makeshift_machete",
     "machete",
     "fencing_epee",
     "fencing_sabre",
     "broadsword_inferior",
     "cutlass_fake",
     "cutlass_inferior",
     "katana_fake",
     "katana_inferior",
     "zweihander_fake",
     "zweihander_inferior",
     "broadsword_fake",
     "rapier_fake",
     "wakizashi_fake",
     "wakizashi_inferior",
     "kris_fake",
     "battleaxe_fake",
     "nodachi_fake",
     "jian",
     "jian_inferior",
     "jian_fake",
     "scimitar",
     "scimitar_inferior",
     "scimitar_fake",
     "estoc",
     "estoc_fake",
     "longsword_inferior",
     "longsword_fake",
     "arming_sword",
     "arming_sword_fake",
     "arming_sword_inferior",
     "battleaxe_inferior",
     "firemachete_off",
     "firemachete_on",
     "pike",
     "battleaxe",
     "longsword",
     "knuckle_katar",
     "knuckle_nail",
     "battletorch_done",
     "crowbar",
     "makeshift_crowbar",
     "shishkebab_off",
     "shishkebab_on",
     "glass_macuahuitl",
     "makeshift_knife",
     "rebar",
     "spear_rebar",
     "spear_knife",
     "spear_wood",
     "spear_forked",
     "spear_copper",
     "spear_steel",
     "spear_survivor",
     "qiang",
     "halberd",
     "halberd_fake",
     "glaive",
     "naginata",
     "mace",
     "morningstar",
     "javelin",
     "javelin_iron",
     "nailbat",
     "nailboard",
     "bwirebat",
     "homewrecker",
     "bowling_axe",
     "baton-extended",
     "PR24-extended"
      ]
    },
  {
   "id":"style_mastery",
   "type": "martial_art",
   "name": "Weapon Mastery",
   "description": "No tool is beyond your reach.",
   "initiate": [ "You become the battlemaster.", "%s assumes posture."],
   "arm_block": 1,
   "leg_block": 1,
   "static_buffs": [
     {
       "id":"style_mastery_proficiency",
       "name": "Weapon Profiiency",
       "description": "You know the in and outs of this weapon, it's balancing. As such you move faster, each action more deft.",
       "min_melee": 5
     }
   ],
   "onmove_buffs": [],
   "techniques": [ "WBLOCK_1", "WBLOCK_2", "DEF_DISARM", "GRAB", "SPIN", "WIDE", "IMPALE", "BRUTAL", "RAPID", "SWEEP", "PRECISE" ],
   "weapons":[
     "avm_sword",
     "avm_blade",
     "avm_greatsword",
     "avm_spear",
     "avm_staff",
     "avm_hammer",
     "avm_baton",
     "avm_mace",
     "sword_wood",
     "sword_nail",
     "sword_crude",
     "firekatana_off",
     "firekatana_on",
     "katana",
     "bokken",
     "cudgel",
     "q_staff",
     "i_staff",
     "lajatang",
     "wakizashi",
     "broadfire_off",
     "broadfire_on",
     "broadsword",
     "cutlass",
     "kris",
     "knife_combat",
     "knife_rambo",
     "knife_rm42",
     "knife_trench",
     "kukri",
     "tanto",
     "punch_dagger",
     "bagh_nakha",
     "cestus",
     "knuckle_brass",
     "knuckle_steel",
     "combatsaw_off",
     "combatsaw_on",
     "cs_lajatang_off",
     "cs_lajatang_on",
     "scythe",
     "scythe_war",
     "tonfa",
     "tonfa_wood",
     "survivor_machete",
     "makeshift_machete",
     "machete",
     "fencing_epee",
     "fencing_sabre",
     "broadsword_inferior",
     "cutlass_fake",
     "cutlass_inferior",
     "katana_fake",
     "katana_inferior",
     "zweihander_fake",
     "zweihander_inferior",
     "broadsword_fake",
     "rapier_fake",
     "wakizashi_fake",
     "wakizashi_inferior",
     "kris_fake",
     "battleaxe_fake",
     "nodachi_fake",
     "jian",
     "jian_inferior",
     "jian_fake",
     "scimitar",
     "scimitar_inferior",
     "scimitar_fake",
     "estoc",
     "estoc_fake",
     "longsword_inferior",
     "longsword_fake",
     "arming_sword",
     "arming_sword_fake",
     "arming_sword_inferior",
     "battleaxe_inferior",
     "firemachete_off",
     "firemachete_on",
     "pike",
     "battleaxe",
     "longsword",
     "knuckle_katar",
     "knuckle_nail",
     "battletorch_done",
     "crowbar",
     "makeshift_crowbar",
     "shishkebab_off",
     "shishkebab_on",
     "glass_macuahuitl",
     "makeshift_knife",
     "rebar",
     "spear_rebar",
     "spear_knife",
     "spear_wood",
     "spear_forked",
     "spear_copper",
     "spear_steel",
     "spear_survivor",
     "qiang",
     "halberd",
     "halberd_fake",
     "glaive",
     "naginata",
     "mace",
     "morningstar",
     "javelin",
     "javelin_iron",
     "nailbat",
     "nailboard",
     "bwirebat",
     "homewrecker",
     "bowling_axe",
     "baton-extended",
     "PR24-extended"
    ]
  },
  {
     "id": "style_eskrima",
     "copy-from": "style_eskrima",
     "type": "martial_art",
     "name": "Eskrima",
     "//": "small weapon, smack",
     "extend": {
       "weapons": [
       "avm_baton",
       "avm_blade"
        ]
      }
  },
  {
    "id": "style_biojutsu",
    "copy-from": "style_biojutsu",
    "type": "martial_art",
    "name": "Bionic Combatives",
    "//": "small and big weapon",
    "extend": {
      "weapons": [
      "avm_sword",
      "avm_staff",
      "avm_baton"
       ]
     }
  },
  {
   "id": "style_niten",
   "copy-from": "style_niten",
   "type": "martial_art",
   "name": "Niten Ichi-Ryu",
   "extend": {
     "weapons": [
     "avm_sword",
     "avm_blade",
     "avm_greatsword"
      ]
    }
  },
  {
   "id": "style_biojutsu",
   "copy-from": "style_biojutsu",
   "type": "martial_art",
   "name": "Bionic Combatives",
   "//": "sword weapon, slash",
   "extend": {
     "weapons": [
     "avm_sword",
     "avm_blade",
     "avm_baton"
      ]
    }
  },
 {
  "id": "style_silat",
  "copy-from": "style_silat",
  "type": "martial_art",
  "name": "Silat",
  "//": "med weapon, slash",
  "extend": {
    "weapons": [
    "avm_sword",
    "avm_baton",
    "avm_staff",
    "avm_blade"
     ]
   }
},
{
 "id": "style_fencing",
 "copy-from": "style_fencing",
 "type": "martial_art",
 "name": "Fencing",
 "//": "thin weapon, slash",
 "extend": {
   "weapons": [
   "avm_spear",
   "avm_staff"
    ]
  }
},
{
 "id": "style_sojutsu",
 "copy-from": "style_sojutsu",
 "type": "martial_art",
 "name": "Sōjutsu",
 "//": "stab weapon, spear",
 "extend": {
   "weapons": [
   "avm_spear",
   "avm_staff"
    ]
  }
 }
]
